roocs_grids/__init__.py
roocs_grids/grids/cmip6_145x288_scrip.20181001.nc
roocs_grids/grids/cmip6_180x360_scrip.20181001.nc
roocs_grids/grids/cmip6_241x480_scrip.20181001.nc
roocs_grids/grids/cmip6_361x576_scrip.20181001.nc
roocs_grids/grids/cmip6_720x1440_scrip.20181001.nc
roocs_grids/grids/cmip6_721x1440_scrip.20181001.nc
roocs_grids/grids/cmip6_72x144_scrip.20181001.nc
roocs_grids/grids/grid_T127_lsm_binary.nc
roocs_grids/grids/grid_T255.nc
roocs_grids/grids/grid_T31.nc
roocs_grids/grids/grid_T42.nc
roocs_grids/grids/grid_T63_lsm_binary.nc
roocs_grids/grids/land_sea_mask_025degree_ERA5.nc
roocs_grids/grids/land_sea_mask_025degree_binary.nc4
roocs_grids/grids/land_sea_mask_05degree.nc4
roocs_grids/grids/land_sea_mask_1degree.nc4
roocs_grids/grids/land_sea_mask_1degree_binary.nc4
roocs_grids/grids/land_sea_mask_2degree.nc4
roocs_grids/grids/land_sea_mask_2degree_binary.nc4
roocs_grids-0.1.2.dist-info/LICENSE
roocs_grids-0.1.2.dist-info/WHEEL
roocs_grids-0.1.2.dist-info/METADATA
roocs_grids-0.1.2.dist-info/RECORD
