Metadata-Version: 2.1
Name: roocs_grids
Version: 0.1.2
Summary: Grid definitions for the roocs regridder.
Keywords: roocs_grids,regrid,grid,interpolate,cmip
Author-email: Ag Stephens <ag.stephens@stfc.ac.uk>, Martin Schupfner <schupfner@dkrz.de>
Maintainer-email: Carsten Ehbrecht <ehbrecht@dkrz.de>, Trevor James Smith <smith.trevorj@ouranos.ca>
Classifier: Development Status :: 5 - Production/Stable
Classifier: Intended Audience :: Developers
Classifier: Intended Audience :: Science/Research
Classifier: License :: OSI Approved :: BSD License
Classifier: Natural Language :: English
Classifier: Operating System :: OS Independent
Classifier: Programming Language :: Python
Classifier: Programming Language :: Python :: 3
Classifier: Programming Language :: Python :: 3.8
Classifier: Programming Language :: Python :: 3.9
Classifier: Programming Language :: Python :: 3.10
Classifier: Programming Language :: Python :: 3.11
Classifier: Topic :: Scientific/Engineering :: Atmospheric Science
Classifier: Topic :: Scientific/Engineering :: GIS
Classifier: Topic :: Software Development :: Libraries :: Python Modules
Requires-Dist: black ; extra == "dev"
Requires-Dist: bump2version ; extra == "dev"
Requires-Dist: clisops ; extra == "dev"
Requires-Dist: isort ; extra == "dev"
Requires-Dist: pytest>=7.0.0 ; extra == "dev"
Requires-Dist: ruff>=0.1.0 ; extra == "dev"
Requires-Dist: xarray ; extra == "dev"
Project-URL: About ROOCS, https://roocs.github.io/
Project-URL: Changelog, https://github.com/roocs/roocs-grids/blob/main/HISTORY.rst
Project-URL: Issue tracker, https://github.com/roocs/roocs-grids/issues
Project-URL: Source, https://github.com/roocs/roocs-grids/
Provides-Extra: dev
